<annotation>
	<folder>train</folder>
	<filename>100051.jpg</filename>
	<path>C:\Users\cwang16\Desktop\train\100051.jpg</path>
	<source>
		<database>Unknown</database>
	</source>
	<size>
		<width>768</width>
		<height>768</height>
		<depth>3</depth>
	</size>
	<segmented>0</segmented>
	<object>
		<name>lm</name>
		<pose>Unspecified</pose>
		<truncated>0</truncated>
		<difficult>0</difficult>
		<bndbox>
			<xmin>323</xmin>
			<ymin>189</ymin>
			<xmax>422</xmax>
			<ymax>302</ymax>
		</bndbox>
	</object>
	<object>
		<name>lm</name>
		<pose>Unspecified</pose>
		<truncated>0</truncated>
		<difficult>0</difficult>
		<bndbox>
			<xmin>419</xmin>
			<ymin>296</ymin>
			<xmax>523</xmax>
			<ymax>417</ymax>
		</bndbox>
	</object>
	<object>
		<name>lm</name>
		<pose>Unspecified</pose>
		<truncated>0</truncated>
		<difficult>0</difficult>
		<bndbox>
			<xmin>355</xmin>
			<ymin>424</ymin>
			<xmax>449</xmax>
			<ymax>536</ymax>
		</bndbox>
	</object>
	<object>
		<name>lm</name>
		<pose>Unspecified</pose>
		<truncated>0</truncated>
		<difficult>0</difficult>
		<bndbox>
			<xmin>227</xmin>
			<ymin>418</ymin>
			<xmax>325</xmax>
			<ymax>521</ymax>
		</bndbox>
	</object>
	<object>
		<name>lm</name>
		<pose>Unspecified</pose>
		<truncated>0</truncated>
		<difficult>0</difficult>
		<bndbox>
			<xmin>207</xmin>
			<ymin>285</ymin>
			<xmax>305</xmax>
			<ymax>391</ymax>
		</bndbox>
	</object>
</annotation>
