<annotation>
	<folder>JPEGImages</folder>
	<filename>300095.jpg</filename>
	<path>E:\2018_Summer\Project\root\s3\VOC2011 (10X)\JPEGImages\300095.jpg</path>
	<source>
		<database>Unknown</database>
	</source>
	<size>
		<width>672</width>
		<height>606</height>
		<depth>3</depth>
	</size>
	<segmented>0</segmented>
	<object>
		<name>lm</name>
		<pose>Unspecified</pose>
		<truncated>0</truncated>
		<difficult>0</difficult>
		<bndbox>
			<xmin>233</xmin>
			<ymin>180</ymin>
			<xmax>314</xmax>
			<ymax>266</ymax>
		</bndbox>
	</object>
	<object>
		<name>lm</name>
		<pose>Unspecified</pose>
		<truncated>0</truncated>
		<difficult>0</difficult>
		<bndbox>
			<xmin>342</xmin>
			<ymin>168</ymin>
			<xmax>422</xmax>
			<ymax>252</ymax>
		</bndbox>
	</object>
	<object>
		<name>lm</name>
		<pose>Unspecified</pose>
		<truncated>0</truncated>
		<difficult>0</difficult>
		<bndbox>
			<xmin>160</xmin>
			<ymin>249</ymin>
			<xmax>232</xmax>
			<ymax>320</ymax>
		</bndbox>
	</object>
	<object>
		<name>lm</name>
		<pose>Unspecified</pose>
		<truncated>0</truncated>
		<difficult>0</difficult>
		<bndbox>
			<xmin>352</xmin>
			<ymin>282</ymin>
			<xmax>446</xmax>
			<ymax>380</ymax>
		</bndbox>
	</object>
	<object>
		<name>lm</name>
		<pose>Unspecified</pose>
		<truncated>0</truncated>
		<difficult>0</difficult>
		<bndbox>
			<xmin>172</xmin>
			<ymin>345</ymin>
			<xmax>246</xmax>
			<ymax>416</ymax>
		</bndbox>
	</object>
	<object>
		<name>lm</name>
		<pose>Unspecified</pose>
		<truncated>0</truncated>
		<difficult>0</difficult>
		<bndbox>
			<xmin>268</xmin>
			<ymin>347</ymin>
			<xmax>362</xmax>
			<ymax>445</ymax>
		</bndbox>
	</object>
</annotation>
