<annotation>
	<folder>JPEGImages</folder>
	<filename>100084.jpg</filename>
	<path>C:\Users\xukun\Desktop\JPEGImages\100084.jpg</path>
	<source>
		<database>Unknown</database>
	</source>
	<size>
		<width>1032</width>
		<height>954</height>
		<depth>3</depth>
	</size>
	<segmented>0</segmented>
	<object>
		<name>root</name>
		<pose>Unspecified</pose>
		<truncated>0</truncated>
		<difficult>0</difficult>
		<bndbox>
			<xmin>114</xmin>
			<ymin>38</ymin>
			<xmax>929</xmax>
			<ymax>896</ymax>
		</bndbox>
	</object>
	<object>
		<name>stele</name>
		<pose>Unspecified</pose>
		<truncated>0</truncated>
		<difficult>0</difficult>
		<bndbox>
			<xmin>429</xmin>
			<ymin>366</ymin>
			<xmax>610</xmax>
			<ymax>569</ymax>
		</bndbox>
	</object>
</annotation>
